FRAKE/FRAKE.py
FRAKE/__init__.py
FRAKE_extractor-1.0.1.dist-info/LICENSE
FRAKE_extractor-1.0.1.dist-info/METADATA
FRAKE_extractor-1.0.1.dist-info/WHEEL
FRAKE_extractor-1.0.1.dist-info/top_level.txt
FRAKE_extractor-1.0.1.dist-info/RECORD
