Metadata-Version: 2.1
Name: FRAKE-extractor
Version: 1.0.1
Summary: "Fusional Real-time Automatic Keyword Extraction"
Home-page: https://github.com/me/myproject
Author: AidinZe
Author-email: a@zehtab.ir
License: MIT
Platform: UNKNOWN
Classifier: License :: OSI Approved :: MIT License
Classifier: Programming Language :: Python
Classifier: Programming Language :: Python :: 3
Classifier: Programming Language :: Python :: 3.6
Classifier: Programming Language :: Python :: Implementation :: PyPy
Requires-Python: >=3.6.0
Requires-Dist: networkx
Requires-Dist: numpy
Requires-Dist: pandas
Requires-Dist: scikit-learn
Requires-Dist: nltk
Requires-Dist: matplotlib
